dm21cm/__init__.py
dm21cm/dh_wrapper.py
dm21cm/evolve.py
dm21cm/interpolators.py
dm21cm/physics.py
dm21cm/profiler.py
dm21cm/tf_wrapper.py
dm21cm/utils.py
dm21cm/xray_cache.py
dm21cm/injections/__init__.py
dm21cm/injections/base.py
dm21cm/injections/decay.py
dm21cm/injections/dm.py
dm21cm/injections/modifiers.py
dm21cm/injections/pbh.py
dm21cm/injections/zero.py
dm21cm/precompute/__init__.py
dm21cm/precompute/accretion.py
dm21cm/precompute/halo.py
dm21cm/precompute/ps.py
dm21cm/precompute/pbh_hr/__init__.py
dm21cm/precompute/pbh_hr/hadronize.py
dm21cm/precompute/pbh_hr/pppc.py
dm21cm/precompute/pbh_hr/read.py
dm21cm/precompute/scripts/build_hmf_tables.py
dm21cm/precompute/scripts/build_pbhacc_tables.py
dm21cm/precompute/scripts/build_pbhhr_tables.py
dm21cm/precompute/scripts/build_pwave_tables.py
dm21cm/precompute/scripts/build_rBeff_tables.py
dm21cm-1.1.0.20250929.dist-info/licenses/LICENSE
dm21cm-1.1.0.20250929.dist-info/METADATA
dm21cm-1.1.0.20250929.dist-info/WHEEL
dm21cm-1.1.0.20250929.dist-info/top_level.txt
dm21cm-1.1.0.20250929.dist-info/RECORD
