Metadata-Version: 2.4
Name: dm21cm
Version: 1.1.0.20250929
Summary: DM21cm - Inhomogeneous Energy Injection in 21-cm Cosmology
Project-URL: Homepage, https://github.com/yitiansun/dm21cm
Requires-Python: >=3.10
License-File: LICENSE
Requires-Dist: astropy>=5.3
Requires-Dist: darkhistory<2.0.0,>=1.1.2
Requires-Dist: h5py>=3.9
Requires-Dist: jax>=0.4.14
Requires-Dist: jaxlib
Requires-Dist: matplotlib>=3.7
Requires-Dist: numpy>=1.25.2
Requires-Dist: pytest
Requires-Dist: powerbox>=0.7.3
Requires-Dist: scipy>=1.11.2
Requires-Dist: tqdm
Dynamic: license-file
